[
  {
    "a": {
      "start": 152722,
      "end": 152800,
      "text": "den in dem Hafen von Girgt , der\nHaupt\u017ftadt von Ober- Aegypten. Die\u017fe Stadt,\n"
    },
    "b": {
      "start": 135680,
      "end": 135758,
      "text": "ber,\nin dem Hafen von Girge, der Hauptstadt von Ober-\nAegypten, die unter der"
    }
  },
  {
    "a": {
      "start": 290207,
      "end": 290373,
      "text": "melucken zu kaufen, die denn\nan dem Gick ihrer Herren Theil nehmen, und\nes bef\u00f6rdern. Nun haben \u017fie nur noch einen Schritt\nbis zu der W\u00fcrde eines Beys, die ihnen ein"
    },
    "b": {
      "start": 575411,
      "end": 575582,
      "text": " Mamlu:\nken kaufen, die dann an dem Gl\u00fccke ihrer Herren Theil\nnahmen, und es bef\u00f6rderten. Nun hatten sie nur noch\nEinen Schritt bis zu der W\u00fcrde eines Beys, in wel\ncher s"
    }
  },
  {
    "a": {
      "start": 299273,
      "end": 299425,
      "text": "hreibt der Pforte: der neue Statthalter\nkomme mit feindlichen Ab\u017fichten, die unter ihren\ngetreuen Unterthanen leicht eine Rebellion erregen\nk\u00f6nnten. Zu"
    },
    "b": {
      "start": 577232,
      "end": 577384,
      "text": "rieb der Pforte: \u201eder neue Statthalter komme\n\u201emit feindlichen Absichten, die unter den getreuen. Unter\n\u201ethanen leicht eine Rebellion erregen k\u00f6nnten,\u201c "
    }
  },
  {
    "a": {
      "start": 289900,
      "end": 290011,
      "text": "e kommen\nnach und nach durch ver\u017fchiedene Stufen zu den\nBedienungen der Beys, und gew\u00f6hnlich \u017fchwin-\ngen \u017fie \u017f"
    },
    "b": {
      "start": 575150,
      "end": 575261,
      "text": "amen fie nach und nach durch verschiedene Stufen zu\nden Bedienungen der Beys, und gew\u00f6hnlich schwangen sie\nsic"
    }
  },
  {
    "a": {
      "start": 293748,
      "end": 293823,
      "text": "ntliche Ausga-\nen f\u00fcr die Unterhaltung der Can\u00e4le und Fe\u017ftun-\ngen vor\u017fch\u00fct"
    },
    "b": {
      "start": 572621,
      "end": 572696,
      "text": "ch\ngro\u00dfe Ausgaben f\u00fcr die Unterhaltung der Kan\u00e4le und Fer\nfungen vor, und "
    }
  },
  {
    "a": {
      "start": 286434,
      "end": 286509,
      "text": "n, denen Kindern, die von Kaufleuten\noder R\u00e4ubern aus Georgien, Circa\u017f\u017ften"
    },
    "b": {
      "start": 573544,
      "end": 573619,
      "text": "t man\ndie Kinder, die von Kaufleuten oder R\u00e4ubern aus Georg\ngien, Tscherka"
    }
  },
  {
    "a": {
      "start": 298202,
      "end": 298325,
      "text": " mi\u00dfbrauchen \u017fie auf das \u00e4u\u00dfers\ne. Ein Pa\u017fcha beh\u00e4lt \u017feine Stelle nur \u017fo lange,\nls er ihre Ab\u017fichten beg\u00fcn\u017ftigt. Wenn er d"
    },
    "b": {
      "start": 576309,
      "end": 576433,
      "text": "nd\nmisbrauchten sie aufs \u00e4u\u00dferste. Ein Baffa behielt\nfeine Stelle nur so lange, als er ihre Absichten beg\u00fcn\nftigte. So wie "
    }
  },
  {
    "a": {
      "start": 285554,
      "end": 285707,
      "text": "\u017feinen per\u017f\u00f6nlichen Eigen\u017fchaften\nab, und er konnte \u017feine Macht nicht auf \u017feine\nKinder vererben, wenn die\u017fe nicht ausgezeichnete\nTalente be\u017fa\u00dfen. Wirkli"
    },
    "b": {
      "start": 571120,
      "end": 571273,
      "text": "os von\npers\u00f6nlichen Eigenschaften ab, und er konnte feine Gewalt\nnicht auf feine S\u00f6hne vererben, wenn diese nicht ausgef\nzeichnete Talente besa\u00dfen; dahe"
    }
  },
  {
    "a": {
      "start": 287341,
      "end": 287414,
      "text": "le von chri\u017ft-\nlichen Familien her. Wenn man \u017fie gekauft hat,\nzwingt man"
    },
    "b": {
      "start": 574158,
      "end": 574231,
      "text": "ten aus christlichen Fami\nlien her. Wenn man sie gekauft hatte, musten s"
    }
  },
  {
    "a": {
      "start": 286524,
      "end": 286623,
      "text": " den \u00fcbrigen Provinzen des ottomani-\n\u017fchen Reichs entf\u00fchrt, und dann zu Con\u017ftantino-\npel und Gro\u00df-"
    },
    "b": {
      "start": 573632,
      "end": 573729,
      "text": "n und andern Provinzen des ,\nosmanischen Reichs entf\u00fchrt, und dann zu Konstantino\npel oder Kairo"
    }
  },
  {
    "a": {
      "start": 284218,
      "end": 284321,
      "text": "h-\nDie Vornehm\u017ften unter ihren w\u00e4hlten \u017fich ein\nOberhaupt, dem \u017fie gro\u00dfes An\u017fehen \u00fcbertrugen.\nEr hatte"
    },
    "b": {
      "start": 570985,
      "end": 571088,
      "text": "n. Die Vornehmsten unter ihnen\nw\u00e4hlten sich ein Oberhaupt, dem fie gro\u00dfes Ansehen \u00fcber\ntrugen; aber di"
    }
  },
  {
    "a": {
      "start": 288745,
      "end": 288819,
      "text": "mit \u017fie das hei\u00dfe Klima\nund den verzehrenden Dur\u017ft in den W\u00fc\u017fte\u00f1 ertra-\ng"
    },
    "b": {
      "start": 574779,
      "end": 574853,
      "text": "r gegen das hei\u00dfe Klima und den\nverzehrenden Durst in den W\u00fcsten. Um vort"
    }
  },
  {
    "a": {
      "start": 291563,
      "end": 291677,
      "text": "r\nzu gewinnen. In die\u017fer Ab\u017ficht ver\u00e4nderte er we-\nnig an ihrer Regierungsform, und bewilligte ih-\nnen gro\u00dfe Priv"
    },
    "b": {
      "start": 571962,
      "end": 572076,
      "text": "n zu\ngewinnen. In dieser Absicht ver\u00e4nderte er wenig an ihr\nrer Regierungsform, und bewilligte ihnen durch einen\n"
    }
  },
  {
    "a": {
      "start": 288474,
      "end": 288562,
      "text": "ich alle b\u00fcrgerliche, militairi\u017fche und gei\u017ftli-\nche W\u00fcrden bekleiden. -\nAuch lehrt man"
    },
    "b": {
      "start": 574488,
      "end": 574576,
      "text": "ort alle b\u00fcrgerliche, mili-\ntairische und geistliche W\u00fcrden bekleiden. -\nAufe\n\nN\n---\n40"
    }
  },
  {
    "a": {
      "start": 287074,
      "end": 287156,
      "text": ".\nDas Ge\u017fetz hier\u00fcber i\u017ft \u017fo be\u017ftimmt, da\u00df der\nSohn eines Beys nicht zu die\u017fer ho"
    },
    "b": {
      "start": 573935,
      "end": 574017,
      "text": "; das Gesetz hier\u00fcber war fo bestimmt, da\u00df der Sohn\neines Beys nicht wieder zu di"
    }
  },
  {
    "a": {
      "start": 298380,
      "end": 298456,
      "text": "will, \u017fo wird er ein Staatsverbrecher. Der\nDivan ver\u017fammelt \u017fich, und man \u017f"
    },
    "b": {
      "start": 576509,
      "end": 576585,
      "text": "eidigen, ward\ner ein Staatsverbrecher; der Divan versammelte sich,\nund schi"
    }
  },
  {
    "a": {
      "start": 299020,
      "end": 299093,
      "text": "r-\n\n\nx2\nerfahren, was f\u00fcr Befehle er zu \u00fcberbringen Haf.\nFinden \u017fie die\u017f"
    },
    "b": {
      "start": 576934,
      "end": 577007,
      "text": "hten zu erfahren, was f\u00fcr\nBefehle er zu \u00fcberbringen h\u00e4tte. Fanden sie so"
    }
  },
  {
    "a": {
      "start": 305274,
      "end": 305347,
      "text": "k zu begeben, und da-\n\u017felb\u017ft Befehle von Con\u017ftantinopel zu erwarten.\nGew"
    },
    "b": {
      "start": 578421,
      "end": 578494,
      "text": "m Nil) begeben, und dafelbst Befehle von Kons\nfantinopel erwarten. -\nSo "
    }
  }
]