[
  {
    "a": {
      "start": 946746,
      "end": 946821,
      "text": " -\n- - \u00d6STERREICHISCHE\n- - -\n- NATIONALBIBLIOTHEK\n- -\n\u2013==-\n- : -\n- * - - -"
    },
    "b": {
      "start": 756848,
      "end": 756923,
      "text": "--\n- - -\n-\n\u00d6STERREICHISCHE -\n| NATIONAL.BIBLIOTHEK\n- - - - - -\n- - - -----"
    }
  },
  {
    "a": {
      "start": 620168,
      "end": 620327,
      "text": "\u00b7 *\n*\uff01---\n*\n\n\n\n{\n \"status code\" : 404,\n \"message\" : \"The requested resource was not found. Either the id or the page on this id doesn't exist.\"\n}\n{\n \"status c"
    },
    "b": {
      "start": 211957,
      "end": 212116,
      "text": ".\n. .\n-\n-\n--\n\n\n{\n \"status code\" : 404,\n \"message\" : \"The requested resource was not found. Either the id or the page on this id doesn't exist.\"\n}\nnach Neu-S\u00fcd"
    }
  },
  {
    "a": {
      "start": 620172,
      "end": 620458,
      "text": "*\uff01---\n*\n\n\n\n{\n \"status code\" : 404,\n \"message\" : \"The requested resource was not found. Either the id or the page on this id doesn't exist.\"\n}\n{\n \"status code\" : 404,\n \"message\" : \"The requested resource was not found. Either the id or the page on this id doesn't exist.\"\n}\nZ ). die Reg"
    },
    "b": {
      "start": 776,
      "end": 933,
      "text": "on Frwing.\n\n{\n \"status code\" : 404,\n \"message\" : \"The requested resource was not found. Either the id or the page on this id doesn't exist.\"\n}\nVerehrungsw\u00fcr"
    }
  },
  {
    "a": {
      "start": 620172,
      "end": 620329,
      "text": "*\uff01---\n*\n\n\n\n{\n \"status code\" : 404,\n \"message\" : \"The requested resource was not found. Either the id or the page on this id doesn't exist.\"\n}\n{\n \"status cod"
    },
    "b": {
      "start": 32809,
      "end": 32966,
      "text": " Rei\u017fe. A\n\n{\n \"status code\" : 404,\n \"message\" : \"The requested resource was not found. Either the id or the page on this id doesn't exist.\"\n}\nGouverneur Phi"
    }
  },
  {
    "a": {
      "start": 620172,
      "end": 620327,
      "text": "*\uff01---\n*\n\n\n\n{\n \"status code\" : 404,\n \"message\" : \"The requested resource was not found. Either the id or the page on this id doesn't exist.\"\n}\n{\n \"status c"
    },
    "b": {
      "start": 407776,
      "end": 407931,
      "text": "hre 1747.\n\n{\n \"status code\" : 404,\n \"message\" : \"The requested resource was not found. Either the id or the page on this id doesn't exist.\"\n}\nBemerkungen\n"
    }
  }
]