[
  {
    "a": {
      "start": 14180,
      "end": 14252,
      "text": "len D\nA\n \n\nvnd Seelnder in Ot Indien\n Daszweyte Capitel\nVon der Stadtvn"
    },
    "b": {
      "start": 11467,
      "end": 11539,
      "text": "om\nZ\nDas\n\nvnnd Seelnder in Ot Indien\nDas zweyte Capitel\nVon Neiver Zurt"
    }
  },
  {
    "a": {
      "start": 379,
      "end": 473,
      "text": "hiffahrten\nGedruckt zu Franckurtam Mayndurch Mathis\n Beckernin Verlegung LeuiniHulj\nWittibim "
    },
    "b": {
      "start": 229,
      "end": 323,
      "text": "um Hulium\n\nGedruckzuFranckfurtam Mayndurch Matthis\nBeckern in Verlegung Leuini Hul \nWittib im"
    }
  }
]