[
  {
    "a": {
      "start": 494448,
      "end": 494568,
      "text": "Fama,\nSie \u017fcheinen wenig\u017ftens \u017fo gro\u00df zu\n\u017feyn, als der Abulhon, oder der\nSphynr, welcher Cairo gegen \u00fcber\ni\u017ft.\u00bb Wansleb"
    },
    "b": {
      "start": 628440,
      "end": 628561,
      "text": "nnen. Sie scheinen\nwenigstens so gro\u00df zu sein, als der Abulhon oder der\nSpinx , , welcher Kairo gegen \u00fcber liegt. Nahe b"
    }
  },
  {
    "a": {
      "start": 1246942,
      "end": 1247014,
      "text": "e 7. \u017foll zuer\u017ft in\nAlexandrien das Evangelium geprediget, und\nder er\u017ft"
    },
    "b": {
      "start": 120159,
      "end": 120231,
      "text": "rkus habe zuerst in Alexandrien das Evan- -\ngelium geprediget und die e"
    }
  }
]