[
  {
    "a": {
      "start": 0,
      "end": 73,
      "text": ". K. H O F B| B|| (C) T\u2013 E K\nOSTERR NATIONAL BIBLIOTHEK\n\n\n\n\n\n-\ne-\n-\n--\n-"
    },
    "b": {
      "start": 36,
      "end": 109,
      "text": " K. H O F B| B L| O T H E K\nOSTERR. NATIONALBIBLIOTHEK\n\n2. Y5\n\n-\u2013\n\n\n\n--\n"
    }
  },
  {
    "a": {
      "start": 528,
      "end": 613,
      "text": " h- n.\n\n- W e im a r,-\nim Verlage des Gr. H. S. priv. Landes-Industrie-Comptoirs.\n1 "
    },
    "b": {
      "start": 668,
      "end": 753,
      "text": "Meere.\n\nW e i m a r,\n- im Verlage des H, S. privil. Landes- Industrie- Comptoirs,\nI "
    }
  }
]