[
  {
    "a": {
      "start": 628508,
      "end": 628589,
      "text": "de,\n\n---\n\nW e im ar,\nim Verlage des F. S. privil. Landes- Indu\u017ftrie-Comptoirs,\n*"
    },
    "b": {
      "start": 530,
      "end": 611,
      "text": "- n.\n\n- W e im a r,-\nim Verlage des Gr. H. S. priv. Landes-Industrie-Comptoirs.\n"
    }
  },
  {
    "a": {
      "start": 1404,
      "end": 1477,
      "text": "des F. S. pr. Landes Indu\u017ftrie Comptoirs.\nI 8 O 4.\u00ab\n\n\n\n\uff0c\uff0c\n\n\n\n-\n\n/\n\n/\n\nVo"
    },
    "b": {
      "start": 568,
      "end": 641,
      "text": ". H. S. priv. Landes-Industrie-Comptoirs.\n1 8 2 O.\n\n\n\n-\n\n-\n\n-\n\n-\n\n-\n-\n\n-"
    }
  }
]