[
  {
    "a": {
      "start": 464801,
      "end": 464874,
      "text": " Erdboden mit\nKreuzwei\u017fe \u00fcbereinander ge\u017fchlagenen Bei-\nnen: auf der ein"
    },
    "b": {
      "start": 71504,
      "end": 71577,
      "text": "beitenden mit kreuzwei\u017fe \u00fcberein-\nder ge\u017fchlagenen Beinen auf Pol\u017ftern a"
    }
  },
  {
    "a": {
      "start": 464800,
      "end": 464872,
      "text": "m Erdboden mit\nKreuzwei\u017fe \u00fcbereinander ge\u017fchlagenen Bei-\nnen: auf der e"
    },
    "b": {
      "start": 237348,
      "end": 237420,
      "text": "r \u017fitzen mit Kreuzwei\u017fe \u00fcbereinan-\nder ge\u017fchlagenen Beinen, wo nur ein "
    }
  }
]